Metadata-Version: 2.1
Name: type-asserter
Version: 1.0.0
Summary: This package enforces the functions' type hints at runtime, making sure that the types of the actual parameters and the return value match the types specified in the function signature.
Home-page: https://github.com/ValerioNeriGit/type_asserter.git
Author: Valerio Neri
Author-email: valerioneri1997@gmail.com
License: MIT
Download-URL: https://github.com/user/reponame/archive/type-asserter_v1.0.0.tar.gz
Keywords: TYPE,TYPES,ASSERTION,TYPE ASSERTION,TYPE CHECKER
Platform: UNKNOWN
Classifier: Development Status :: 4 - Beta
Classifier: Intended Audience :: Developers
Classifier: Topic :: Software Development :: Build Tools
Classifier: License :: OSI Approved :: MIT License
Classifier: Programming Language :: Python :: 3.8
Classifier: Programming Language :: Python :: 3.9
